card_component_st_test/__init__.py
card_component_st_test/frontend/build/asset-manifest.json
card_component_st_test/frontend/build/bootstrap.min.css
card_component_st_test/frontend/build/index.html
card_component_st_test/frontend/build/precache-manifest.06cde483dbfc00cc5108b21b332a1ebe.js
card_component_st_test/frontend/build/service-worker.js
card_component_st_test/frontend/build/static/css/2.c2b20982.chunk.css
card_component_st_test/frontend/build/static/css/2.c2b20982.chunk.css.map
card_component_st_test/frontend/build/static/js/2.12682af3.chunk.js
card_component_st_test/frontend/build/static/js/2.12682af3.chunk.js.LICENSE.txt
card_component_st_test/frontend/build/static/js/2.12682af3.chunk.js.map
card_component_st_test/frontend/build/static/js/main.c5955c96.chunk.js
card_component_st_test/frontend/build/static/js/main.c5955c96.chunk.js.map
card_component_st_test/frontend/build/static/js/runtime-main.44d30fc2.js
card_component_st_test/frontend/build/static/js/runtime-main.44d30fc2.js.map
card_component_st_test/frontend/build/static/media/roboto-all-300-normal.2323284e.woff
card_component_st_test/frontend/build/static/media/roboto-all-400-normal.62b936e1.woff
card_component_st_test/frontend/build/static/media/roboto-all-500-normal.68d75d95.woff
card_component_st_test/frontend/build/static/media/roboto-all-700-normal.aa462125.woff
card_component_st_test/frontend/build/static/media/roboto-cyrillic-300-normal.9b9ec295.woff2
card_component_st_test/frontend/build/static/media/roboto-cyrillic-400-normal.d9ac47c7.woff2
card_component_st_test/frontend/build/static/media/roboto-cyrillic-500-normal.7b08b9e1.woff2
card_component_st_test/frontend/build/static/media/roboto-cyrillic-700-normal.6f112ec2.woff2
card_component_st_test/frontend/build/static/media/roboto-cyrillic-ext-300-normal.d0441335.woff2
card_component_st_test/frontend/build/static/media/roboto-cyrillic-ext-400-normal.c00467dc.woff2
card_component_st_test-0.0.1.dist-info/LICENSE
card_component_st_test-0.0.1.dist-info/METADATA
card_component_st_test-0.0.1.dist-info/WHEEL
card_component_st_test-0.0.1.dist-info/top_level.txt
card_component_st_test-0.0.1.dist-info/RECORD
